django_genshi
