Metadata-Version: 1.0
Name: django-genshi
Version: 1.1.3
Summary: Django integration for Genshi
Home-page: https://launchpad.net/django-genshi
Author: John Millikin
Author-email: jmillikin@gmail.com
License: GPL
Download-URL: http://pypi.python.org/pypi/django-genshi/1.1.3
Keywords: django,genshi
Platform: Platform Independent
Classifier: Development Status :: 4 - Beta
Classifier: Framework :: Django
Classifier: Intended Audience :: Developers
Classifier: License :: OSI Approved :: GNU General Public License (GPL)
Classifier: Operating System :: OS Independent
Classifier: Programming Language :: Python
Classifier: Topic :: Internet :: WWW/HTTP :: Dynamic Content
Classifier: Topic :: Software Development :: Libraries :: Python Modules
Classifier: Topic :: Text Processing :: Markup :: HTML
Classifier: Topic :: Text Processing :: Markup :: XML
